wayne/__init__.py
wayne/speak_fiasto.py
wayne/trade_formula_for_matrix.py
wayne_trade-0.1.8.dist-info/licenses/LICENSE
wayne_trade-0.1.8.dist-info/METADATA
wayne_trade-0.1.8.dist-info/WHEEL
wayne_trade-0.1.8.dist-info/top_level.txt
wayne_trade-0.1.8.dist-info/RECORD
