Metadata-Version: 2.4
Name: wayne-trade
Version: 0.1.8
Summary: Formula to model matrix converter
Author-email: Alex Hallam <alexhallam628@gmail.com>
License: MIT
Requires-Python: >=3.13
License-File: LICENSE
Requires-Dist: polars>=1.8.2
Requires-Dist: numpy>=1.21.0
Requires-Dist: fiasto-py>=0.1.4
Provides-Extra: dev
Requires-Dist: pytest>=7.0.0; extra == "dev"
Requires-Dist: pytest-cov>=4.0.0; extra == "dev"
Dynamic: license-file
